[
  {
    "team_code": "11",
    "team_name": "BUKBU",
    "players": [
      { "NAME": "원종혁", "BackNum": "48" },
      { "NAME": "한지헌", "BackNum": "1" },
      { "NAME": "김웅", "BackNum": "129" },
      { "NAME": "김종운", "BackNum": "49" },
      { "NAME": "박시원", "BackNum": "121.1" },
      { "NAME": "김한중", "BackNum": "121.2" },
      { "NAME": "박연준", "BackNum": "120" },
      { "NAME": "임진묵", "BackNum": "82" },
      { "NAME": "정세영", "BackNum": "77" },
      { "NAME": "허인서", "BackNum": "59" },
      { "NAME": "이율예", "BackNum": "32" },
      { "NAME": "김성우", "BackNum": "44" },
      { "NAME": "배승수", "BackNum": "98" },
      { "NAME": "최윤석", "BackNum": "94.1" },
      { "NAME": "손용준", "BackNum": "52" },
      { "NAME": "김준상", "BackNum": "94.2" },
      { "NAME": "한다현", "BackNum": "114" },
      { "NAME": "양현종", "BackNum": "70" },
      { "NAME": "이민재", "BackNum": "57" },
      { "NAME": "박정빈", "BackNum": "58" },
      { "NAME": "이승민", "BackNum": "9" },
      { "NAME": "최우혁", "BackNum": "119" },
      { "NAME": "심휘윤", "BackNum": "91" },
      { "NAME": "한지윤", "BackNum": "67" }
    ]
  },
  {
    "team_code": "12",
    "team_name": "NAMBU",
    "players": [
      { "NAME": "홍승원", "BackNum": "41" },
      { "NAME": "강건", "BackNum": "99" },
      { "NAME": "김재원", "BackNum": "43" },
      { "NAME": "김대호", "BackNum": "44" },
      { "NAME": "정민성", "BackNum": "49" },
      { "NAME": "김준원", "BackNum": "106" },
      { "NAME": "노재원", "BackNum": "110" },
      { "NAME": "이영재", "BackNum": "103" },
      { "NAME": "이도현", "BackNum": "66" },
      { "NAME": "윤준호", "BackNum": "11" },
      { "NAME": "신민우", "BackNum": "117" },
      { "NAME": "박재엽", "BackNum": "63" },
      { "NAME": "류현인", "BackNum": "21" },
      { "NAME": "김재상", "BackNum": "12" },
      { "NAME": "이승현", "BackNum": "96" },
      { "NAME": "이창용", "BackNum": "50" },
      { "NAME": "정현창", "BackNum": "52" },
      { "NAME": "이태경", "BackNum": "69" },
      { "NAME": "김병준", "BackNum": "57" },
      { "NAME": "함수호", "BackNum": "40" },
      { "NAME": "김동현", "BackNum": "64" },
      { "NAME": "박재현", "BackNum": "36.1" },
      { "NAME": "박헌", "BackNum": "36.2" },
      { "NAME": "이영재", "BackNum": "9" }
    ]
  },
  {
    "team_code": "13",
    "team_name": "DREAM",
    "players": [
      { "NAME": "박세웅", "BackNum": "21" },
      { "NAME": "베찬승", "BackNum": "55" },
      { "NAME": "김원중", "BackNum": "34" },
      { "NAME": "이호성", "BackNum": "1.1" },
      { "NAME": "김택연", "BackNum": "63" },
      { "NAME": "박치국", "BackNum": "1.2" },
      { "NAME": "박영현", "BackNum": "60" },
      { "NAME": "우규민", "BackNum": "12" },
      { "NAME": "이로운", "BackNum": "92" },
      { "NAME": "조병현", "BackNum": "19" },
      { "NAME": "강민호", "BackNum": "47" },
      { "NAME": "장성우", "BackNum": "22" },
      { "NAME": "조형우", "BackNum": "20" },
      { "NAME": "디아즈", "BackNum": "0" },
      { "NAME": "류지혁", "BackNum": "16" },
      { "NAME": "최정", "BackNum": "14" },
      { "NAME": "전민재", "BackNum": "13" },
      { "NAME": "오명진", "BackNum": "6" },
      { "NAME": "권동진", "BackNum": "52" },
      { "NAME": "구자욱", "BackNum": "5" },
      { "NAME": "레이예스", "BackNum": "29" },
      { "NAME": "김지찬", "BackNum": "58" },
      { "NAME": "배정대", "BackNum": "27" },
      { "NAME": "안현민", "BackNum": "23" },
      { "NAME": "전준우", "BackNum": "8" }
    ]
  },
  {
    "team_code": "14",
    "team_name": "NANUM",
    "players": [
      { "NAME": "폰세", "BackNum": "30.1" },
      { "NAME": "박상원", "BackNum": "58" },
      { "NAME": "김서현", "BackNum": "44" },
      { "NAME": "윤영철", "BackNum": "13" },
      { "NAME": "최지민", "BackNum": "39" },
      { "NAME": "김영우", "BackNum": "67" },
      { "NAME": "박명근", "BackNum": "39" },
      { "NAME": "배재환", "BackNum": "61" },
      { "NAME": "주승우", "BackNum": "30.2" },
      { "NAME": "하영민", "BackNum": "50" },
      { "NAME": "박동원", "BackNum": "27" },
      { "NAME": "김태군", "BackNum": "42" },
      { "NAME": "김형준", "BackNum": "25" },
      { "NAME": "채은성", "BackNum": "22.1" },
      { "NAME": "박민우", "BackNum": "2.1" },
      { "NAME": "송성문", "BackNum": "24" },
      { "NAME": "박찬호", "BackNum": "1" },
      { "NAME": "이도윤", "BackNum": "7.1" },
      { "NAME": "김주원", "BackNum": "7.2" },
      { "NAME": "박해민", "BackNum": "17" },
      { "NAME": "이주형", "BackNum": "2.2" },
      { "NAME": "박건우", "BackNum": "37" },
      { "NAME": "김현수", "BackNum": "22.2" },
      { "NAME": "문현빈", "BackNum": "51" },
      { "NAME": "최형우", "BackNum": "34" }
    ]
  }
]