{
  "record-base-name": "2025_11_27_23_40_31",
  "product-date": "20251127",
  "product-time": "234050",
  "product-name": "234050_23XI Racing - Team_23",
  "product-target": "23XI Racing - Team_23",
  "product-save-path": "\\\\10.82.104.210\\Output/234050_23XI Racing - Team_23",
  "use-audio": false,
  "product-start-time": "2025-11-27 23:40:50",
  "output": {
    "resolution": "FHD",
    "codec": "H.264",
    "fps": "30",
    "bitrate": "15",
    "gop": "30",
    "output_path": "\\\\10.82.104.210\\Output"
  },
  "record-info": "/record/history/recorded/2025_11_27_23_40_31.json"
}